alom/__init__.py
alom/exceptions.py
alom/metrics.py
alom/parse.py
alom/ssh.py
alom_exporter-0.0.7.dist-info/LICENSE.txt
alom_exporter-0.0.7.dist-info/METADATA
alom_exporter-0.0.7.dist-info/WHEEL
alom_exporter-0.0.7.dist-info/entry_points.txt
alom_exporter-0.0.7.dist-info/top_level.txt
alom_exporter-0.0.7.dist-info/RECORD
