Metadata-Version: 2.1
Name: alom-exporter
Version: 0.0.7
Summary: Prometheus exporter for Sun ALOM statistics
Home-page: https://github.com/delucks/alom_exporter
Author: delucks
Author-email: me@jamieluck.com
License: GPLv3
Download-URL: https://github.com/delucks/alom_exporter/tarball/0.0.7
Keywords: prometheus,sun,oracle,sparc,alom,prometheus exporter
Platform: UNKNOWN
Classifier: Development Status :: 3 - Alpha
Classifier: Environment :: Console
Classifier: Intended Audience :: Developers
Classifier: Intended Audience :: Science/Research
Classifier: Intended Audience :: System Administrators
Classifier: License :: OSI Approved :: GNU General Public License v3 (GPLv3)
Classifier: Natural Language :: English
Classifier: Operating System :: MacOS :: MacOS X
Classifier: Operating System :: POSIX :: Linux
Classifier: Operating System :: POSIX :: BSD
Classifier: Programming Language :: Python :: 3 :: Only
Classifier: Topic :: System :: Monitoring
Classifier: Topic :: System :: Systems Administration
Classifier: Topic :: Utilities
Requires-Python: >=3.6
Requires-Dist: paramiko (==2.7.2)
Requires-Dist: PyYAML (>=5.4)
Requires-Dist: prometheus-client (==0.8.0)
